sherpa_client/__init__.py
sherpa_client/api/__init__.py
sherpa_client/api/alt_texts/__init__.py
sherpa_client/api/alt_texts/delete_alt_texts_by_name.py
sherpa_client/api/alt_texts/get_alt_texts.py
sherpa_client/api/annotate/__init__.py
sherpa_client/api/annotate/annotate_binary_with_plan.py
sherpa_client/api/annotate/annotate_binary_with_project.py
sherpa_client/api/annotate/annotate_binary_with_project_annotator.py
sherpa_client/api/annotate/annotate_corpus_with.py
sherpa_client/api/annotate/annotate_documents_with_plan.py
sherpa_client/api/annotate/annotate_documents_with_project_annotator.py
sherpa_client/api/annotate/annotate_format_binary_with_plan.py
sherpa_client/api/annotate/annotate_format_binary_with_project_annotator.py
sherpa_client/api/annotate/annotate_format_documents_with_plan.py
sherpa_client/api/annotate/annotate_format_documents_with_project_annotator.py
sherpa_client/api/annotate/annotate_format_text_with_plan.py
sherpa_client/api/annotate/annotate_format_text_with_project_annotator.py
sherpa_client/api/annotate/annotate_text_with_plan.py
sherpa_client/api/annotate/annotate_text_with_project.py
sherpa_client/api/annotate/annotate_text_with_project_annotator.py
sherpa_client/api/annotate/deprecated_annotate_binary_with_plan_ref.py
sherpa_client/api/annotate/deprecated_annotate_documents_with.py
sherpa_client/api/annotate/deprecated_annotate_format_binary_with_plan_ref.py
sherpa_client/api/annotate/deprecated_annotate_format_documents_with_plan_ref.py
sherpa_client/api/annotate/deprecated_annotate_format_text_with_plan_ref.py
sherpa_client/api/annotate/deprecated_annotate_text.py
sherpa_client/api/annotate/deprecated_annotate_text_with.py
sherpa_client/api/annotate/format_binary.py
sherpa_client/api/annotations/__init__.py
sherpa_client/api/annotations/annotation_creators_count.py
sherpa_client/api/annotations/clear_annotations.py
sherpa_client/api/annotations/count_annotations.py
sherpa_client/api/annotations/create_annotation.py
sherpa_client-1.0.3.dist-info/LICENSE
sherpa_client-1.0.3.dist-info/METADATA
sherpa_client-1.0.3.dist-info/WHEEL
sherpa_client-1.0.3.dist-info/RECORD
